{
    "activityid": 14402,
    "fields": {
        "Type": "Presentation",
        "Title of Presentation": "Philosophical Foundations of Physical Education in Idaho",
        "Conference/Meeting Name": "Idaho Education Network Physical Education Day",
        "Conference Location": "Boise, Idaho",
        "Date or Date Range": "2012-02-28",
        "Actual/Projected Year of Publication/Presentation": 2012,
        "Sponsoring Organization": "Idaho State Department of Education",
        "Presenter(s)": null,
        "Web Address": "",
        "Description/Abstract": "",
        "Origin": "Other"
    },
    "facultyid": "112179883",
    "coauthors": {
        "61476": {
            "firstname": "Tyler",
            "middleinitial": "",
            "lastname": "Johnson",
            "percentcontribution": "0",
            "sameschoolflag": 1,
            "facultyid": "112179883",
            "authorid": 61476,
            "scholarlyactivityid": 14402
        }
    },
    "status": [
        {
            "id": 14402,
            "status": "Completed/Published",
            "term": "Spring",
            "year": 2012,
            "termid": "2011/03",
            "listingorder": 6,
            "completionorder": 6
        }
    ],
    "userid": "112179883",
    "attachments": []
}