{
    "activityid": 17256,
    "fields": {
        "Type": "Poster Presentation",
        "Title of Presentation": "Drought Effects on Colonization of Artemisia tridentata seedlings by Arbuscular Mycorrhizal Fungi",
        "Conference / Meeting Name": "Undergraduate research conference",
        "Conference Location": "Boise, ID",
        "Date or Date Range": "2015-04-20",
        "Actual/Projected Year of Publication/Presentation": 2015,
        "Sponsoring Organization": "Boise State University",
        "Presenter(s)": null,
        "Web Address": "1910 University Drive",
        "Description/Abstract": "",
        "Origin": "Other"
    },
    "facultyid": "111116958",
    "coauthors": {
        "67942": {
            "firstname": "Joel",
            "middleinitial": "",
            "lastname": "Velasco",
            "percentcontribution": "0",
            "sameschoolflag": 0,
            "facultyid": null,
            "authorid": 67942,
            "scholarlyactivityid": 17256
        },
        "67943": {
            "firstname": "Marcelo",
            "middleinitial": "",
            "lastname": "Serpe",
            "percentcontribution": "0",
            "sameschoolflag": 1,
            "facultyid": "111116958",
            "authorid": 67943,
            "scholarlyactivityid": 17256
        }
    },
    "status": [
        {
            "id": 17256,
            "status": "Completed/Published",
            "term": "Spring",
            "year": 2015,
            "termid": "2014/03",
            "listingorder": 6,
            "completionorder": 6
        }
    ],
    "userid": "111116958",
    "attachments": []
}