{
    "activityid": 17774,
    "fields": {
        "Type": "Presentation",
        "Title of Presentation": "Exploring multicultural nonfiction books for children: Criticial content analysis of nonfiction books about Korea",
        "Conference/Meeting Name": "American Educational research Association",
        "Conference Location": "New Orelans, LA",
        "Date or Date Range": "2011-04-30",
        "Actual/Projected Year of Publication/Presentation": 2011,
        "Sponsoring Organization": "",
        "Presenter(s)": null,
        "Web Address": "",
        "Description/Abstract": "",
        "Origin": "Other"
    },
    "facultyid": "112180267",
    "coauthors": {
        "69251": {
            "firstname": "EunHye",
            "middleinitial": "",
            "lastname": "Son",
            "percentcontribution": "0",
            "sameschoolflag": 1,
            "facultyid": "112180267",
            "authorid": 69251,
            "scholarlyactivityid": 17774
        },
        "69252": {
            "firstname": "Yoo Kyung",
            "middleinitial": "",
            "lastname": "Sung",
            "percentcontribution": "0",
            "sameschoolflag": 0,
            "facultyid": null,
            "authorid": 69252,
            "scholarlyactivityid": 17774
        }
    },
    "status": [
        {
            "id": 17774,
            "status": "Completed/Published",
            "term": "Spring",
            "year": 2011,
            "termid": "2010/03",
            "listingorder": 6,
            "completionorder": 6
        }
    ],
    "userid": "112180267",
    "attachments": []
}