{
    "activityid": 19810,
    "fields": {
        "Type": "Presentation",
        "Title of Presentation": "HR Roundtable",
        "Conference/Meeting Name": "Snake River Society for Human Resource Management Conference",
        "Conference Location": "Twin Falls, Idaho",
        "Date or Date Range": "2011-09-30",
        "Actual/Projected Year of Publication/Presentation": 2011,
        "Sponsoring Organization": "Society for Human Resource Management",
        "Presenter(s)": null,
        "Web Address": "",
        "Description/Abstract": "",
        "Origin": "Other"
    },
    "facultyid": "111110548",
    "coauthors": {
        "73219": {
            "firstname": "Gundars",
            "middleinitial": "",
            "lastname": "Kaupins",
            "percentcontribution": "0",
            "sameschoolflag": 1,
            "facultyid": "111110548",
            "authorid": 73219,
            "scholarlyactivityid": 19810
        }
    },
    "status": [
        {
            "id": 19810,
            "status": "Completed/Published",
            "term": "Fall",
            "year": 2011,
            "termid": "2011/02",
            "listingorder": 6,
            "completionorder": 6
        }
    ],
    "userid": "111110548",
    "attachments": []
}