{
    "activityid": 21147,
    "fields": {
        "Type": "Poster Presentation",
        "Title of Presentation": "Development of immunohistochemical methods for investigation of the role of caspase activity in bone",
        "Conference / Meeting Name": "Annual INBRE Summer Research Conference poster Undergraduate Research Meeting",
        "Conference Location": "",
        "Date or Date Range": "2011-08-02",
        "Actual/Projected Year of Publication/Presentation": 2011,
        "Sponsoring Organization": "",
        "Presenter(s)": null,
        "Web Address": "",
        "Description/Abstract": "",
        "Origin": "Other"
    },
    "facultyid": "111643741",
    "coauthors": {
        "76277": {
            "firstname": "L",
            "middleinitial": "",
            "lastname": "Catlin",
            "percentcontribution": "0",
            "sameschoolflag": 1,
            "facultyid": "111702712",
            "authorid": 76277,
            "scholarlyactivityid": 21147
        },
        "76278": {
            "firstname": "B",
            "middleinitial": "",
            "lastname": "Davis",
            "percentcontribution": "0",
            "sameschoolflag": 0,
            "facultyid": null,
            "authorid": 76278,
            "scholarlyactivityid": 21147
        },
        "76279": {
            "firstname": "Julia",
            "middleinitial": "Thom",
            "lastname": "Oxford",
            "percentcontribution": "0",
            "sameschoolflag": 1,
            "facultyid": "111643744",
            "authorid": 76279,
            "scholarlyactivityid": 21147
        },
        "76280": {
            "firstname": "Troy",
            "middleinitial": "T",
            "lastname": "Rohn",
            "percentcontribution": "0",
            "sameschoolflag": 1,
            "facultyid": "111643741",
            "authorid": 76280,
            "scholarlyactivityid": 21147
        }
    },
    "status": [
        {
            "id": 21147,
            "status": "Completed/Published",
            "term": "Summer",
            "year": 2011,
            "termid": "2011/01",
            "listingorder": 6,
            "completionorder": 6
        }
    ],
    "userid": "111643741",
    "attachments": []
}