{
    "activityid": 24932,
    "fields": {
        "Type": "Review",
        "Title of Review": "Literarisch Europa erkunden: Thomas Geigers Anthologie \u2018Luftspr\u00fcnge\u2019",
        "Actual/Projected Year of Publication/Presentation": 2015,
        "Page Numbers of Number of Pages": "",
        "Publisher": "Literaturkritik.de",
        "Publisher Location": " ",
        "Month / Season": "2015-09-30",
        "Title of larger work": "",
        "Volume": "14",
        "Issue Number": "10",
        "Author/Editor of larger work": "",
        "DOI": "",
        "ISSN/ISBN #": "1437-9317",
        "Author(s) / Editor(s)": null,
        "Web Address": "http://www.literaturkritik.de/public/rezension.php?rez_id=21021",
        "Description/Abstract": "Review of an anthology that explores Europe through literary texts.",
        "Origin": "Other"
    },
    "facultyid": "111110237",
    "coauthors": {
        "90595": {
            "firstname": "Heike",
            "middleinitial": "",
            "lastname": "Henderson",
            "percentcontribution": "",
            "sameschoolflag": 1,
            "facultyid": "111110237",
            "authorid": 90595,
            "scholarlyactivityid": 24932
        }
    },
    "status": [
        {
            "id": 24932,
            "status": "Completed/Published",
            "term": "Fall",
            "year": 2015,
            "termid": "2015/02",
            "listingorder": 6,
            "completionorder": 6
        }
    ],
    "userid": "111110237",
    "attachments": []
}