{
    "activityid": 26585,
    "fields": {
        "Type": "Conference Proceeding",
        "Title of Contribution": "Teaching Online: Meeting the Challenge with Emerging Strategies for Effective Professional Development. ",
        "Name of Conference": "",
        "Month / Season": "2008-12-31",
        "Actual/Projected Year of Publication/Presentation": 2008,
        "Page Numbers": "",
        "Publisher": "American Association for Computers in Education",
        "Publisher Location": "Chesapeake, VA USA",
        "Volume": "",
        "Issue Number": "",
        "DOI": "",
        "ISBN/ISSN #": "",
        "Contributor": null,
        "Web Address": "",
        "Description/Abstract": "",
        "Origin": "Other"
    },
    "facultyid": "111146699",
    "coauthors": {
        "85061": {
            "firstname": "Kerry",
            "middleinitial": "Lynn",
            "lastname": "Rice",
            "percentcontribution": "0",
            "sameschoolflag": 1,
            "facultyid": "111146699",
            "authorid": 85061,
            "scholarlyactivityid": 26585
        },
        "85062": {
            "firstname": "Donna",
            "middleinitial": "",
            "lastname": "Vakili-Hutchison",
            "percentcontribution": "0",
            "sameschoolflag": 0,
            "facultyid": null,
            "authorid": 85062,
            "scholarlyactivityid": 26585
        }
    },
    "status": [
        {
            "id": 26585,
            "status": "Completed/Published",
            "term": "Fall",
            "year": 2008,
            "termid": "2008/02",
            "listingorder": 6,
            "completionorder": 6
        }
    ],
    "userid": "111146699",
    "attachments": []
}