{
    "activityid": 27194,
    "fields": {
        "Type": "Presentation",
        "Title of Presentation": "The Effects Of Power and Sourcing Philosophy on Supplier Performance",
        "Conference/Meeting Name": "North American Research and Teaching Symposium",
        "Conference Location": " ",
        "Date or Date Range": "2009-12-31",
        "Actual/Projected Year of Publication/Presentation": 2010,
        "Sponsoring Organization": "",
        "Presenter(s)": null,
        "Web Address": "",
        "Description/Abstract": "Explanation of Other:  Conference Proceeding",
        "Origin": "Other"
    },
    "facultyid": "112095616",
    "coauthors": {
        "117383": {
            "firstname": "Regis",
            "middleinitial": "",
            "lastname": "Terpend",
            "percentcontribution": "",
            "sameschoolflag": 1,
            "facultyid": "112095616",
            "authorid": 117383,
            "scholarlyactivityid": 27194
        },
        "117384": {
            "firstname": "Bryan",
            "middleinitial": "",
            "lastname": "Ashenbaum",
            "percentcontribution": "",
            "sameschoolflag": 0,
            "facultyid": null,
            "authorid": 117384,
            "scholarlyactivityid": 27194
        }
    },
    "status": [
        {
            "id": 27194,
            "status": "Completed/Published",
            "term": "Spring",
            "year": 2010,
            "termid": "2009/03",
            "listingorder": 6,
            "completionorder": 6
        }
    ],
    "userid": "112095616",
    "attachments": []
}