{
    "activityid": 29386,
    "fields": {
        "Type": "Presentation",
        "Title of Presentation": "Saying Goodbye to Education: Compulsory Schooling and the Enforcement of the Big Other",
        "Conference/Meeting Name": "Invited Presentation at Utah Valley State Annual Honors Colloquium",
        "Conference Location": "Utah Valley State",
        "Date or Date Range": "March 6, 2017",
        "Actual/Projected Year of Publication/Presentation": 2017,
        "Sponsoring Organization": "Utah Valley University Honors Program",
        "Presenter(s)": null,
        "Web Address": "",
        "Description/Abstract": "",
        "Origin": "Manual"
    },
    "facultyid": "114002258",
    "coauthors": {
        "156001": {
            "firstname": "David",
            "middleinitial": "A",
            "lastname": "Gabbard",
            "percentcontribution": "",
            "sameschoolflag": 1,
            "facultyid": "114002258",
            "authorid": 156001,
            "scholarlyactivityid": 29386
        }
    },
    "status": [
        {
            "id": 29386,
            "status": "Completed/Published",
            "term": "Spring",
            "year": 2018,
            "termid": "2017/03",
            "listingorder": 6,
            "completionorder": 6
        }
    ],
    "userid": "114002258",
    "attachments": []
}