{
    "activityid": 31685,
    "fields": {
        "Type": "Presentation",
        "Title of Presentation": "Making Mathematics Meaningful",
        "Conference/Meeting Name": "i-STEM Summer Institute",
        "Conference Location": "Twin Falls, Idaho",
        "Date or Date Range": "",
        "Actual/Projected Year of Publication/Presentation": 2016,
        "Sponsoring Organization": "",
        "Presenter(s)": null,
        "Web Address": "",
        "Description/Abstract": "",
        "Origin": "Manual"
    },
    "facultyid": "113017246",
    "coauthors": {
        "119828": {
            "firstname": "Laurie",
            "middleinitial": "O",
            "lastname": "Cavey",
            "percentcontribution": "",
            "sameschoolflag": 1,
            "facultyid": "113017246",
            "authorid": 119828,
            "scholarlyactivityid": 31685
        }
    },
    "status": [
        {
            "id": 31685,
            "status": "Completed/Published",
            "term": "Summer",
            "year": 2016,
            "termid": "2016/01",
            "listingorder": 6,
            "completionorder": 6
        }
    ],
    "userid": "113017246",
    "attachments": []
}