{
    "activityid": 33430,
    "fields": {
        "Type": "Journal Publication",
        "Title of Contribution": "Rotary kiln incineration. Comparison and scaling of field-scale and pilot-scale contaminant evolution rates from sorbent beds",
        "Journal": "Environmental science &amp; technology",
        "Volume": "25",
        "Month / Season": "",
        "Issue Number": "6",
        "Actual/Projected Year of Publication/Presentation": 1991,
        "Page Numbers": "1142--1152",
        "Publisher": "",
        "DOI": "",
        "PubMed Central ID Number": "",
        "Author(s) / Editor(s)": null,
        "Web Address": "",
        "Description/Abstract": "",
        "Origin": "BibTeX"
    },
    "facultyid": "114087590",
    "coauthors": {
        "133885": {
            "firstname": "Thomas",
            "middleinitial": "W",
            "lastname": "Lester",
            "percentcontribution": "",
            "sameschoolflag": 0,
            "facultyid": null,
            "authorid": 133885,
            "scholarlyactivityid": 33430
        },
        "133886": {
            "firstname": "Vic",
            "middleinitial": "A",
            "lastname": "Cundy",
            "percentcontribution": "",
            "sameschoolflag": 0,
            "facultyid": null,
            "authorid": 133886,
            "scholarlyactivityid": 33430
        },
        "133887": {
            "firstname": "Arthur",
            "middleinitial": "M",
            "lastname": "Sterling",
            "percentcontribution": "",
            "sameschoolflag": 0,
            "facultyid": null,
            "authorid": 133887,
            "scholarlyactivityid": 33430
        },
        "133888": {
            "firstname": "Alfred",
            "middleinitial": "N",
            "lastname": "Montestruc",
            "percentcontribution": "",
            "sameschoolflag": 0,
            "facultyid": null,
            "authorid": 133888,
            "scholarlyactivityid": 33430
        },
        "133889": {
            "firstname": "Allen",
            "middleinitial": "L",
            "lastname": "Jakway",
            "percentcontribution": "",
            "sameschoolflag": 0,
            "facultyid": null,
            "authorid": 133889,
            "scholarlyactivityid": 33430
        },
        "133890": {
            "firstname": "Chao",
            "middleinitial": "",
            "lastname": "Lu",
            "percentcontribution": "",
            "sameschoolflag": 0,
            "facultyid": null,
            "authorid": 133890,
            "scholarlyactivityid": 33430
        },
        "133891": {
            "firstname": "Christopher",
            "middleinitial": "B",
            "lastname": "Leger",
            "percentcontribution": "",
            "sameschoolflag": 0,
            "facultyid": null,
            "authorid": 133891,
            "scholarlyactivityid": 33430
        },
        "133892": {
            "firstname": "David",
            "middleinitial": "W",
            "lastname": "Pershing",
            "percentcontribution": "",
            "sameschoolflag": 0,
            "facultyid": null,
            "authorid": 133892,
            "scholarlyactivityid": 33430
        },
        "133893": {
            "firstname": "JoAnn",
            "middleinitial": "S",
            "lastname": "Lighty",
            "percentcontribution": "",
            "sameschoolflag": 0,
            "facultyid": null,
            "authorid": 133893,
            "scholarlyactivityid": 33430
        }
    },
    "status": [
        {
            "id": 33430,
            "status": "Completed/Published",
            "term": "Summer",
            "year": 1991,
            "termid": "1991/01",
            "listingorder": 6,
            "completionorder": 6
        }
    ],
    "userid": "114087590",
    "attachments": []
}