{
    "activityid": 33486,
    "fields": {
        "Type": "Presentation",
        "Title of Presentation": "Characterization of the properties of soot for aromatic and aliphatic flames",
        "Conference/Meeting Name": "5th US Combustion Meeting 2007",
        "Conference Location": "",
        "Date or Date Range": "",
        "Actual/Projected Year of Publication/Presentation": 2007,
        "Sponsoring Organization": "",
        "Presenter(s)": null,
        "Web Address": "",
        "Description/Abstract": "",
        "Origin": "BibTeX"
    },
    "facultyid": "114087590",
    "coauthors": {
        "137430": {
            "firstname": "C",
            "middleinitial": "A",
            "lastname": "Echavarria",
            "percentcontribution": "",
            "sameschoolflag": 0,
            "facultyid": null,
            "authorid": 137430,
            "scholarlyactivityid": 33486
        },
        "137431": {
            "firstname": "A",
            "middleinitial": "",
            "lastname": "Sarofim",
            "percentcontribution": "",
            "sameschoolflag": 0,
            "facultyid": null,
            "authorid": 137431,
            "scholarlyactivityid": 33486
        },
        "137432": {
            "firstname": "Z",
            "middleinitial": "",
            "lastname": "Yang",
            "percentcontribution": "",
            "sameschoolflag": 0,
            "facultyid": null,
            "authorid": 137432,
            "scholarlyactivityid": 33486
        },
        "137433": {
            "firstname": "J",
            "middleinitial": "",
            "lastname": "Lighty",
            "percentcontribution": "",
            "sameschoolflag": 0,
            "facultyid": null,
            "authorid": 137433,
            "scholarlyactivityid": 33486
        }
    },
    "status": [
        {
            "id": 33486,
            "status": "Completed/Published",
            "term": "Summer",
            "year": 2007,
            "termid": "2007/01",
            "listingorder": 6,
            "completionorder": 6
        }
    ],
    "userid": "114087590",
    "attachments": []
}