{
    "activityid": 34396,
    "fields": {
        "Type": "Journal Publication",
        "Title of Contribution": "Establishing Doctoral Programs in Electrical Engineering, Materials Science and Engineering, and Computing in an Emerging Research Institution: Lessons Learned and Best Practices",
        "Journal": null,
        "Volume": null,
        "Month / Season": null,
        "Issue Number": null,
        "Actual/Projected Year of Publication/Presentation": 2017,
        "Page Numbers": null,
        "Publisher": null,
        "DOI": null,
        "PubMed Central ID Number": null,
        "Author(s) / Editor(s)": null,
        "Web Address": null,
        "Description/Abstract": null,
        "Origin": "BibTeX"
    },
    "facultyid": "111643645",
    "coauthors": {
        "139401": {
            "firstname": "Janet",
            "middleinitial": "",
            "lastname": "Callahan",
            "percentcontribution": null,
            "sameschoolflag": 0,
            "facultyid": null,
            "authorid": 139401,
            "scholarlyactivityid": 34396
        },
        "139402": {
            "firstname": "Cheryl",
            "middleinitial": "B",
            "lastname": "Schrader",
            "percentcontribution": null,
            "sameschoolflag": 0,
            "facultyid": null,
            "authorid": 139402,
            "scholarlyactivityid": 34396
        },
        "139403": {
            "firstname": "Darryl",
            "middleinitial": "P",
            "lastname": "Butt",
            "percentcontribution": null,
            "sameschoolflag": 0,
            "facultyid": null,
            "authorid": 139403,
            "scholarlyactivityid": 34396
        },
        "139404": {
            "firstname": "Timothy",
            "middleinitial": "",
            "lastname": "Anderson",
            "percentcontribution": null,
            "sameschoolflag": 0,
            "facultyid": null,
            "authorid": 139404,
            "scholarlyactivityid": 34396
        },
        "139405": {
            "firstname": "Tammi",
            "middleinitial": "",
            "lastname": "Vacha-Hasse",
            "percentcontribution": null,
            "sameschoolflag": 0,
            "facultyid": null,
            "authorid": 139405,
            "scholarlyactivityid": 34396
        },
        "139406": {
            "firstname": "Amy",
            "middleinitial": "J",
            "lastname": "Moll",
            "percentcontribution": null,
            "sameschoolflag": 0,
            "facultyid": null,
            "authorid": 139406,
            "scholarlyactivityid": 34396
        }
    },
    "status": [
        {
            "id": 34396,
            "status": "Completed/Published",
            "term": "Summer",
            "year": 2017,
            "termid": "2017/01",
            "listingorder": 6,
            "completionorder": 6
        }
    ],
    "userid": "111643645",
    "attachments": []
}