{
    "activityid": 3747,
    "fields": {
        "Type": "Journal Publication",
        "Title of Contribution": "Link Bordism Skein Modules",
        "Journal": "Fundamenta Mathematicae",
        "Volume": "184",
        "Month / Season": "2004-10-01",
        "Issue Number": "",
        "Actual/Projected Year of Publication/Presentation": 2004,
        "Page Numbers": "113-134",
        "Publisher": "",
        "DOI": "http://dx.doi.org/10.4064/fm184-0-9",
        "PubMed Central ID Number": "",
        "Author(s) / Editor(s)": null,
        "Web Address": "http://scholarworks.boisestate.edu/math_facpubs/70",
        "Description/Abstract": "We compute link bordism skein modules of colored oriented links in oriented 3-manifolds. A Hurewicz theorem relating link bordism and link homotopy skein modules is proved.",
        "Origin": "Other"
    },
    "facultyid": "111669772",
    "coauthors": {
        "11025": {
            "firstname": "Uwe",
            "middleinitial": "",
            "lastname": "Kaiser",
            "percentcontribution": "0",
            "sameschoolflag": 1,
            "facultyid": "111669772",
            "authorid": 11025,
            "scholarlyactivityid": 3747
        }
    },
    "status": [
        {
            "id": 3747,
            "status": "Completed/Published",
            "term": "Fall",
            "year": 2004,
            "termid": "2004/02",
            "listingorder": 6,
            "completionorder": 6
        }
    ],
    "userid": "111669772",
    "attachments": []
}