{
    "activityid": 38037,
    "fields": {
        "Type": "Journal Publication",
        "Title of Contribution": "New age constraints for early Paleogene strata of central Patagonia, Argentina: Implications for the timing of South American Land Mammal Ages",
        "Journal": "GEOLOGICAL SOCIETY OF AMERICA BULLETIN",
        "Volume": "129",
        "Month / Season": "JUL-AUG",
        "Issue Number": "7-8",
        "Actual/Projected Year of Publication/Presentation": 2017,
        "Page Numbers": "886-903",
        "Publisher": "",
        "DOI": "",
        "PubMed Central ID Number": "",
        "Author(s) / Editor(s)": null,
        "Web Address": "",
        "Description/Abstract": "",
        "Origin": "Web of Science"
    },
    "facultyid": "112001853",
    "coauthors": {
        "158804": {
            "firstname": "Krause,",
            "middleinitial": "J.",
            "lastname": "Marcelo",
            "percentcontribution": "",
            "sameschoolflag": 0,
            "facultyid": null,
            "authorid": 158804,
            "scholarlyactivityid": 38037
        },
        "158805": {
            "firstname": "William",
            "middleinitial": "C.",
            "lastname": "Clyde",
            "percentcontribution": "",
            "sameschoolflag": 0,
            "facultyid": null,
            "authorid": 158805,
            "scholarlyactivityid": 38037
        },
        "158806": {
            "firstname": "Mauricio",
            "middleinitial": "",
            "lastname": "Ibanez-Mejia",
            "percentcontribution": "",
            "sameschoolflag": 0,
            "facultyid": null,
            "authorid": 158806,
            "scholarlyactivityid": 38037
        },
        "158807": {
            "firstname": "Mark",
            "middleinitial": "D.",
            "lastname": "Schmitz",
            "percentcontribution": "",
            "sameschoolflag": 0,
            "facultyid": null,
            "authorid": 158807,
            "scholarlyactivityid": 38037
        },
        "158808": {
            "firstname": "Timothy",
            "middleinitial": "",
            "lastname": "Barnum",
            "percentcontribution": "",
            "sameschoolflag": 0,
            "facultyid": null,
            "authorid": 158808,
            "scholarlyactivityid": 38037
        },
        "158809": {
            "firstname": "Eduardo",
            "middleinitial": "S.",
            "lastname": "Bellosi",
            "percentcontribution": "",
            "sameschoolflag": 0,
            "facultyid": null,
            "authorid": 158809,
            "scholarlyactivityid": 38037
        },
        "158810": {
            "firstname": "Peter",
            "middleinitial": "",
            "lastname": "Wilf",
            "percentcontribution": "",
            "sameschoolflag": 0,
            "facultyid": null,
            "authorid": 158810,
            "scholarlyactivityid": 38037
        }
    },
    "status": [
        {
            "id": 38037,
            "status": "Completed/Published",
            "term": "Summer",
            "year": 2017,
            "termid": "2017/01",
            "listingorder": 6,
            "completionorder": 6
        }
    ],
    "userid": "112001853",
    "attachments": []
}