{
    "activityid": 38551,
    "fields": {
        "Type": "Presentation",
        "Title of Presentation": "Singular value analysis of Joint Inversion",
        "Conference/Meeting Name": "SIAM Pacific Northwest webinar",
        "Conference Location": "webinar",
        "Date or Date Range": "12/7",
        "Actual/Projected Year of Publication/Presentation": 2018,
        "Sponsoring Organization": "",
        "Presenter(s)": null,
        "Web Address": "",
        "Description/Abstract": "",
        "Origin": "Manual"
    },
    "facultyid": "111643644",
    "coauthors": {
        "162134": {
            "firstname": "Jodi",
            "middleinitial": "L",
            "lastname": "Mead",
            "percentcontribution": "",
            "sameschoolflag": 1,
            "facultyid": "111643644",
            "authorid": 162134,
            "scholarlyactivityid": 38551
        },
        "162135": {
            "firstname": "James",
            "middleinitial": "",
            "lastname": "Ford",
            "percentcontribution": "",
            "sameschoolflag": 0,
            "facultyid": null,
            "authorid": 162135,
            "scholarlyactivityid": 38551
        }
    },
    "status": [
        {
            "id": 38551,
            "status": "Completed/Published",
            "term": "Fall",
            "year": 2017,
            "termid": "2017/02",
            "listingorder": 6,
            "completionorder": 6
        }
    ],
    "userid": "111643644",
    "attachments": []
}