{
    "activityid": 38763,
    "fields": {
        "Type": "Artistic Works and Performances",
        "Work/Exhibit Title": "Solo Piano Performance of B\u00e9la Bart\u00f3k Suite op. 14 (1916)",
        "Name of Performing Group": "Faculty Artist Series:  Chamber Music Recital",
        "Date or Date Range": "February 9, 2018",
        "Actual/Projected Year of Publication/Presentation": 2018,
        "Name of Venue/Sponsor": "Morrison Center Recital Hall",
        "Venue / Sponsor Location (City, State, Country)": "Boise State University, Boise, Idaho",
        "Co-contributor": null,
        "Web address": "",
        "Description/Abstract": "&quot;Front, Aftermath, and Homefront,&quot;a Concert Dedicated to the Hemingway Literary kCenter's commemoration of &quot;100 Years after the 'War to End All Wars'&quot;",
        "Web Address": "",
        "Origin": "Manual"
    },
    "facultyid": "112134675",
    "coauthors": {
        "163577": {
            "firstname": "Mark",
            "middleinitial": "Russell",
            "lastname": "Hansen",
            "percentcontribution": "",
            "sameschoolflag": 1,
            "facultyid": "112134675",
            "authorid": 163577,
            "scholarlyactivityid": 38763,
            "classifications": {
                "Role": "Performer"
            }
        }
    },
    "status": [
        {
            "id": 38763,
            "status": "Completed/Published",
            "term": "Spring",
            "year": 2018,
            "termid": "2017/03",
            "listingorder": 6,
            "completionorder": 6
        }
    ],
    "userid": "112134675",
    "attachments": []
}