{
    "activityid": 47974,
    "fields": {
        "Type": "Artistic Works and Performances",
        "Work/Exhibit Title": "Canela Y Fuego",
        "Name of Performing Group": "Shimi Tree/Escuela de Flamenco",
        "Date or Date Range": "May 19",
        "Actual/Projected Year of Publication/Presentation": 2019,
        "Name of Venue/Sponsor": "Potter Wines",
        "Venue / Sponsor Location (City, State, Country)": "Garden City, Idaho, USA",
        "Co-contributor": null,
        "Web address": "",
        "Description/Abstract": "Instructed guests in basic flamenco dance steps, danced flamenco and played flamenco percussion.",
        "Web Address": "",
        "Origin": "Manual"
    },
    "facultyid": "111702833",
    "coauthors": {
        "221128": {
            "firstname": "Ruth",
            "middleinitial": "",
            "lastname": "Salter",
            "percentcontribution": "",
            "sameschoolflag": 1,
            "facultyid": "111702833",
            "authorid": 221128,
            "scholarlyactivityid": 47974
        }
    },
    "status": [
        {
            "id": 47974,
            "status": "Completed/Published",
            "term": "Summer",
            "year": 2019,
            "termid": "2019/01",
            "listingorder": 6,
            "completionorder": 6
        }
    ],
    "userid": "111702833",
    "attachments": []
}