{
    "activityid": 48379,
    "fields": {
        "Type": "Journal Publication",
        "Title of Contribution": "Interhemispheric radio-astrochronological calibration of the time scales from the Andean and the Tethyan areas in the Valanginian-Hauterivian (Early Cretaceous)",
        "Journal": "GONDWANA RESEARCH",
        "Volume": "70",
        "Month / Season": "JUN",
        "Issue Number": "",
        "Actual/Projected Year of Publication/Presentation": 2019,
        "Page Numbers": "104-132",
        "Publisher": "",
        "DOI": "",
        "PubMed Central ID Number": "",
        "Author(s) / Editor(s)": null,
        "Web Address": "",
        "Description/Abstract": "",
        "Origin": "Web of Science"
    },
    "facultyid": "112001853",
    "coauthors": {
        "224060": {
            "firstname": "Beatriz",
            "middleinitial": "",
            "lastname": "Aguirre-Urreta",
            "percentcontribution": "",
            "sameschoolflag": 0,
            "facultyid": null,
            "authorid": 224060,
            "scholarlyactivityid": 48379
        },
        "224061": {
            "firstname": "Mathieu",
            "middleinitial": "",
            "lastname": "Martinez",
            "percentcontribution": "",
            "sameschoolflag": 0,
            "facultyid": null,
            "authorid": 224061,
            "scholarlyactivityid": 48379
        },
        "224062": {
            "firstname": "Mark",
            "middleinitial": "",
            "lastname": "Schmitz",
            "percentcontribution": "",
            "sameschoolflag": 0,
            "facultyid": null,
            "authorid": 224062,
            "scholarlyactivityid": 48379
        },
        "224063": {
            "firstname": "Marina",
            "middleinitial": "",
            "lastname": "Lescano",
            "percentcontribution": "",
            "sameschoolflag": 0,
            "facultyid": null,
            "authorid": 224063,
            "scholarlyactivityid": 48379
        },
        "224064": {
            "firstname": "Julieta",
            "middleinitial": "",
            "lastname": "Omarini",
            "percentcontribution": "",
            "sameschoolflag": 0,
            "facultyid": null,
            "authorid": 224064,
            "scholarlyactivityid": 48379
        },
        "224065": {
            "firstname": "Maisa",
            "middleinitial": "",
            "lastname": "Tunik",
            "percentcontribution": "",
            "sameschoolflag": 0,
            "facultyid": null,
            "authorid": 224065,
            "scholarlyactivityid": 48379
        },
        "224066": {
            "firstname": "Henning",
            "middleinitial": "",
            "lastname": "Kuhnert",
            "percentcontribution": "",
            "sameschoolflag": 0,
            "facultyid": null,
            "authorid": 224066,
            "scholarlyactivityid": 48379
        },
        "224067": {
            "firstname": "Andrea",
            "middleinitial": "",
            "lastname": "Concheyro",
            "percentcontribution": "",
            "sameschoolflag": 0,
            "facultyid": null,
            "authorid": 224067,
            "scholarlyactivityid": 48379
        },
        "224068": {
            "firstname": "Peter",
            "middleinitial": "F.",
            "lastname": "Rawson",
            "percentcontribution": "",
            "sameschoolflag": 0,
            "facultyid": null,
            "authorid": 224068,
            "scholarlyactivityid": 48379
        },
        "224069": {
            "firstname": "Victor",
            "middleinitial": "A.",
            "lastname": "Ramos",
            "percentcontribution": "",
            "sameschoolflag": 0,
            "facultyid": null,
            "authorid": 224069,
            "scholarlyactivityid": 48379
        },
        "224070": {
            "firstname": "Stephane",
            "middleinitial": "",
            "lastname": "Reboulet",
            "percentcontribution": "",
            "sameschoolflag": 0,
            "facultyid": null,
            "authorid": 224070,
            "scholarlyactivityid": 48379
        },
        "224071": {
            "firstname": "Nicolas",
            "middleinitial": "",
            "lastname": "Noclin",
            "percentcontribution": "",
            "sameschoolflag": 0,
            "facultyid": null,
            "authorid": 224071,
            "scholarlyactivityid": 48379
        },
        "224072": {
            "firstname": "Thomas",
            "middleinitial": "",
            "lastname": "Frederichs",
            "percentcontribution": "",
            "sameschoolflag": 0,
            "facultyid": null,
            "authorid": 224072,
            "scholarlyactivityid": 48379
        },
        "224073": {
            "firstname": "Anna-Leah",
            "middleinitial": "",
            "lastname": "Nickl",
            "percentcontribution": "",
            "sameschoolflag": 0,
            "facultyid": null,
            "authorid": 224073,
            "scholarlyactivityid": 48379
        },
        "224074": {
            "firstname": "Heiko",
            "middleinitial": "",
            "lastname": "Paelike",
            "percentcontribution": "",
            "sameschoolflag": 0,
            "facultyid": null,
            "authorid": 224074,
            "scholarlyactivityid": 48379
        }
    },
    "status": [
        {
            "id": 48379,
            "status": "Completed/Published",
            "term": "Summer",
            "year": 2019,
            "termid": "2019/01",
            "listingorder": 6,
            "completionorder": 6
        }
    ],
    "userid": "112001853",
    "attachments": []
}