{
    "activityid": 51061,
    "fields": {
        "Type": "Artistic Works and Performances",
        "Work/Exhibit Title": "Let's Face It",
        "Name of Performing Group": "",
        "Date or Date Range": "",
        "Actual/Projected Year of Publication/Presentation": 2020,
        "Name of Venue/Sponsor": "Museum of Craft &amp; Design",
        "Venue / Sponsor Location (City, State, Country)": "San Francisco, CA",
        "Co-contributor": null,
        "Web address": "https://sfmcd.org/lfi_communitygallery/",
        "Description/Abstract": "",
        "Web Address": "https://sfmcd.org/lfi_communitygallery/",
        "Origin": "Manual"
    },
    "facultyid": "114028031",
    "coauthors": {
        "235420": {
            "firstname": "Lily",
            "middleinitial": "",
            "lastname": "Lee",
            "percentcontribution": "",
            "sameschoolflag": 1,
            "facultyid": "114028031",
            "authorid": 235420,
            "scholarlyactivityid": 51061
        }
    },
    "status": [
        {
            "id": 51061,
            "status": "Completed/Published",
            "term": "Summer",
            "year": 2020,
            "termid": "2020/01",
            "listingorder": 6,
            "completionorder": 6
        }
    ],
    "userid": "114028031",
    "attachments": []
}