{
    "activityid": 52225,
    "fields": {
        "Type": "Journal Publication",
        "Title of Contribution": "Effect of Sex and Ankle Brace Design on Knee Biomechanics During a Single-Leg Cut",
        "Journal": "The American journal of sports medicine",
        "Volume": "48",
        "Month / Season": null,
        "Issue Number": "6",
        "Actual/Projected Year of Publication/Presentation": 2020,
        "Page Numbers": "1496-1504",
        "Publisher": null,
        "DOI": "10.1177/0363546520911048",
        "PubMed Central ID Number": null,
        "Author(s) / Editor(s)": null,
        "Web Address": null,
        "Description/Abstract": "Despite success at preventing ankle sprain, prophylactics that restrict ankle plantarflexion motion may produce deleterious knee biomechanics and increase injury risk.",
        "Origin": "PubMed"
    },
    "facultyid": "114045105",
    "coauthors": {
        "242188": {
            "firstname": "Wyatt ",
            "middleinitial": "D",
            "lastname": "Ihmels",
            "percentcontribution": null,
            "sameschoolflag": 0,
            "facultyid": null,
            "authorid": 242188,
            "scholarlyactivityid": 52225
        },
        "242189": {
            "firstname": "Kayla ",
            "middleinitial": "D",
            "lastname": "Seymore",
            "percentcontribution": null,
            "sameschoolflag": 0,
            "facultyid": null,
            "authorid": 242189,
            "scholarlyactivityid": 52225
        },
        "242190": {
            "firstname": "Tyler ",
            "middleinitial": "N",
            "lastname": "Brown",
            "percentcontribution": null,
            "sameschoolflag": 0,
            "facultyid": null,
            "authorid": 242190,
            "scholarlyactivityid": 52225
        }
    },
    "status": [
        {
            "id": 52225,
            "status": "Completed/Published",
            "term": "Spring",
            "year": 2020,
            "termid": "2019/03",
            "listingorder": 6,
            "completionorder": 6
        }
    ],
    "userid": "114045105",
    "attachments": []
}