{
    "activityid": 54130,
    "fields": {
        "Type": "Artistic Works and Performances",
        "Work/Exhibit Title": "preparation/memorization of new solo piano repertory",
        "Name of Performing Group": "self",
        "Date or Date Range": "",
        "Actual/Projected Year of Publication/Presentation": 2023,
        "Name of Venue/Sponsor": "Dunkley Music Co.",
        "Venue / Sponsor Location (City, State, Country)": "Boise, ID  USA",
        "Co-contributor": null,
        "Web address": "",
        "Description/Abstract": "",
        "Web Address": "",
        "Origin": "Manual"
    },
    "facultyid": "112134675",
    "coauthors": {
        "253331": {
            "firstname": "Mark",
            "middleinitial": "Russell",
            "lastname": "Hansen",
            "percentcontribution": "",
            "sameschoolflag": 1,
            "facultyid": "112134675",
            "authorid": 253331,
            "scholarlyactivityid": 54130
        }
    },
    "status": [
        {
            "id": 54130,
            "status": "In Progress",
            "term": "Spring",
            "year": 2021,
            "termid": "2020/03",
            "listingorder": 1,
            "completionorder": 1
        },
        {
            "id": 54130,
            "status": "In Progress",
            "term": "Fall",
            "year": 2020,
            "termid": "2020/02",
            "listingorder": 1,
            "completionorder": 1
        }
    ],
    "userid": "112134675",
    "attachments": []
}