{
    "activityid": 54451,
    "fields": {
        "Type": "Journal Publication",
        "Title of Contribution": "Elementary School Teachers\u2019 Professional Development through Facilitating an Integrated STEM Robotics Activity",
        "Journal": "Journal of Computers in Mathematics and Science Teaching",
        "Volume": "39",
        "Month / Season": "",
        "Issue Number": "3",
        "Actual/Projected Year of Publication/Presentation": 2020,
        "Page Numbers": "207-230",
        "Publisher": "",
        "DOI": "https://www.learntechlib.org/primary/p/213317/",
        "PubMed Central ID Number": "",
        "Author(s) / Editor(s)": null,
        "Web Address": "",
        "Description/Abstract": "",
        "Origin": "Manual"
    },
    "facultyid": "114001930",
    "coauthors": {
        "255523": {
            "firstname": "Yu-Hui",
            "middleinitial": "",
            "lastname": "Ching",
            "percentcontribution": null,
            "sameschoolflag": 1,
            "facultyid": "113083497",
            "authorid": 255523,
            "scholarlyactivityid": 54451
        },
        "255522": {
            "firstname": "Sasha",
            "middleinitial": "",
            "lastname": "Wang",
            "percentcontribution": null,
            "sameschoolflag": 1,
            "facultyid": "113118296",
            "authorid": 255522,
            "scholarlyactivityid": 54451
        },
        "255521": {
            "firstname": "Dazhi",
            "middleinitial": "",
            "lastname": "Yang",
            "percentcontribution": null,
            "sameschoolflag": 1,
            "facultyid": "113078547",
            "authorid": 255521,
            "scholarlyactivityid": 54451
        },
        "255520": {
            "firstname": "Youngkyun",
            "middleinitial": "",
            "lastname": "Baek",
            "percentcontribution": null,
            "sameschoolflag": 1,
            "facultyid": "113083482",
            "authorid": 255520,
            "scholarlyactivityid": 54451
        },
        "255519": {
            "firstname": "Bhaskar",
            "middleinitial": "C.S.",
            "lastname": "Chittoori",
            "percentcontribution": null,
            "sameschoolflag": 1,
            "facultyid": "114001930",
            "authorid": 255519,
            "scholarlyactivityid": 54451
        }
    },
    "status": [
        {
            "id": 54451,
            "status": "Completed/Published",
            "term": "Fall",
            "year": 2020,
            "termid": "2020/02",
            "listingorder": 6,
            "completionorder": 6
        }
    ],
    "userid": "114001930",
    "attachments": []
}