{
    "activityid": 59548,
    "fields": {
        "Type": "Presentation",
        "Title of Presentation": "Block-based Logically Cartesian adaptive mesh refinement using p4est",
        "Conference/Meeting Name": "University of California, Santa Barbara",
        "Conference Location": "Virtual",
        "Date or Date Range": "May 2021",
        "Actual/Projected Year of Publication/Presentation": 2021,
        "Sponsoring Organization": "UCSB",
        "Presenter(s)": null,
        "Web Address": "",
        "Description/Abstract": "",
        "Origin": "Manual"
    },
    "facultyid": "113079626",
    "coauthors": {
        "278284": {
            "firstname": "Donna",
            "middleinitial": "",
            "lastname": "Calhoun",
            "percentcontribution": "",
            "sameschoolflag": 1,
            "facultyid": "113079626",
            "authorid": 278284,
            "scholarlyactivityid": 59548
        }
    },
    "status": [
        {
            "id": 59548,
            "status": "Completed/Published",
            "term": "Spring",
            "year": 2021,
            "termid": "2020/03",
            "listingorder": 6,
            "completionorder": 6
        }
    ],
    "userid": "113079626",
    "attachments": []
}