{
    "activityid": 59842,
    "fields": {
        "Type": "Journal Publication",
        "Title of Contribution": "Increasing Heat-Stress Inequality in a Warming Climate",
        "Journal": "Earth's Future",
        "Volume": "10",
        "Month / Season": "2022/03/14",
        "Issue Number": "2",
        "Actual/Projected Year of Publication/Presentation": 2022,
        "Page Numbers": "e2021EF002488",
        "Publisher": null,
        "DOI": null,
        "PubMed Central ID Number": null,
        "Author(s) / Editor(s)": null,
        "Web Address": "https://doi.org/10.1029/2021EF002488",
        "Description/Abstract": null,
        "Origin": "RIS"
    },
    "facultyid": "114080133",
    "coauthors": {
        "279474": {
            "firstname": "Mohammad",
            "middleinitial": "Reza",
            "lastname": "Alizadeh",
            "percentcontribution": null,
            "sameschoolflag": 0,
            "facultyid": null,
            "authorid": 279474,
            "scholarlyactivityid": 59842
        },
        "279475": {
            "firstname": "John",
            "middleinitial": "T.",
            "lastname": "Abatzoglou",
            "percentcontribution": null,
            "sameschoolflag": 0,
            "facultyid": null,
            "authorid": 279475,
            "scholarlyactivityid": 59842
        },
        "279476": {
            "firstname": "Jan",
            "middleinitial": "F.",
            "lastname": "Adamowski",
            "percentcontribution": null,
            "sameschoolflag": 0,
            "facultyid": null,
            "authorid": 279476,
            "scholarlyactivityid": 59842
        },
        "279477": {
            "firstname": "Jeffrey",
            "middleinitial": "P.",
            "lastname": "Prestemon",
            "percentcontribution": null,
            "sameschoolflag": 0,
            "facultyid": null,
            "authorid": 279477,
            "scholarlyactivityid": 59842
        },
        "279478": {
            "firstname": "Bhaskar",
            "middleinitial": "",
            "lastname": "Chittoori",
            "percentcontribution": null,
            "sameschoolflag": 0,
            "facultyid": null,
            "authorid": 279478,
            "scholarlyactivityid": 59842
        },
        "279479": {
            "firstname": "Asanjan,",
            "middleinitial": "Ata",
            "lastname": "Akbari",
            "percentcontribution": null,
            "sameschoolflag": 0,
            "facultyid": null,
            "authorid": 279479,
            "scholarlyactivityid": 59842
        },
        "279480": {
            "firstname": "Mojtaba",
            "middleinitial": "",
            "lastname": "Sadegh",
            "percentcontribution": null,
            "sameschoolflag": 0,
            "facultyid": null,
            "authorid": 279480,
            "scholarlyactivityid": 59842
        }
    },
    "status": [
        {
            "id": 59842,
            "status": "Completed/Published",
            "term": "Summer",
            "year": 2022,
            "termid": "2022/01",
            "listingorder": 6,
            "completionorder": 6
        }
    ],
    "userid": "114080133",
    "attachments": []
}