{
    "activityid": 64984,
    "fields": {
        "Type": "Presentation",
        "Title of Presentation": "&lt;span&gt;&lt;span style=&quot;font-size:11pt;&quot;&gt;Application of data driven models for stream temperature modeling&lt;/span&gt;&lt;/span&gt;",
        "Conference/Meeting Name": "GEM3 ID NSF EPSCoR Annual Meeting",
        "Conference Location": "Boise, ID.",
        "Date or Date Range": "",
        "Actual/Projected Year of Publication/Presentation": 2022,
        "Sponsoring Organization": "",
        "Presenter(s)": null,
        "Web Address": "",
        "Description/Abstract": "",
        "Origin": "Manual"
    },
    "facultyid": "114136569",
    "coauthors": {
        "301329": {
            "firstname": "Tao",
            "middleinitial": "",
            "lastname": "Huang",
            "percentcontribution": "",
            "sameschoolflag": 0,
            "facultyid": null,
            "authorid": 301329,
            "scholarlyactivityid": 64984,
            "classifications": {
                "Role": "Presenter"
            }
        },
        "301330": {
            "firstname": "Megan",
            "middleinitial": "E",
            "lastname": "Cattau",
            "percentcontribution": "",
            "sameschoolflag": 1,
            "facultyid": "114136569",
            "authorid": 301330,
            "scholarlyactivityid": 64984
        }
    },
    "status": [
        {
            "id": 64984,
            "status": "Completed/Published",
            "term": "Fall",
            "year": 2022,
            "termid": "2022/02",
            "listingorder": 6,
            "completionorder": 6
        }
    ],
    "userid": "114136569",
    "attachments": []
}