{
    "activityid": 75045,
    "fields": {
        "Type": "Conference Proceeding",
        "Title of Contribution": "&lt;span style=&quot;color:#222222;font-size:small;&quot;&gt;muRelBench: MicroBenchmarking for Zonotope Domains&lt;/span&gt;",
        "Name of Conference": "Static Analysis Symposium (SAS)",
        "Month / Season": "",
        "Actual/Projected Year of Publication/Presentation": null,
        "Page Numbers": "",
        "Publisher": "",
        "Publisher Location": "",
        "Volume": "",
        "Issue Number": "",
        "DOI": "",
        "ISBN/ISSN #": "",
        "Contributor": null,
        "Web Address": "",
        "Description/Abstract": "",
        "Origin": "Manual"
    },
    "facultyid": "113164447",
    "coauthors": {
        "331762": {
            "firstname": "Kenny",
            "middleinitial": "",
            "lastname": "Ballou",
            "percentcontribution": "",
            "sameschoolflag": 0,
            "facultyid": null,
            "authorid": 331762,
            "scholarlyactivityid": 75045,
            "classifications": {
                "Role": "Graduate Student Researcher"
            }
        },
        "331763": {
            "firstname": "Elena",
            "middleinitial": "A",
            "lastname": "Sherman",
            "percentcontribution": "",
            "sameschoolflag": 1,
            "facultyid": "113164447",
            "authorid": 331763,
            "scholarlyactivityid": 75045,
            "classifications": {
                "Role": "Author"
            }
        }
    },
    "status": [
        {
            "id": 75045,
            "status": "Revise &amp; Resubmit",
            "term": "Spring",
            "year": 2024,
            "termid": "2023/03",
            "listingorder": 3,
            "completionorder": 3
        }
    ],
    "userid": "113164447",
    "attachments": []
}