{
    "activityid": 77223,
    "fields": {
        "Type": "Presentation",
        "Title of Presentation": "Cybersecurity Programs and Initiatives - Research Overview",
        "Conference/Meeting Name": "",
        "Conference Location": "Virtual",
        "Date or Date Range": "December 6, 2024",
        "Actual/Projected Year of Publication/Presentation": 2024,
        "Sponsoring Organization": "",
        "Presenter(s)": null,
        "Web Address": "",
        "Description/Abstract": "&lt;span&gt;By invitation of the Institute for Pervasive Cybersecurity, presented to the Industry Advisory Board a 10 minute talk regarding research work related to cyber security.&lt;/span&gt;",
        "Origin": "Manual"
    },
    "facultyid": "111716691",
    "coauthors": {
        "345718": {
            "firstname": "Liljana",
            "middleinitial": "",
            "lastname": "Babinkostova",
            "percentcontribution": "",
            "sameschoolflag": 1,
            "facultyid": "111716691",
            "authorid": 345718,
            "scholarlyactivityid": 77223,
            "classifications": {
                "Role": "Presenter"
            }
        }
    },
    "status": [
        {
            "id": 77223,
            "status": "Completed/Published",
            "term": "Fall",
            "year": 2024,
            "termid": "2024/02",
            "listingorder": 6,
            "completionorder": 6
        }
    ],
    "userid": "111716691",
    "attachments": []
}